Flask_MicroServices-0.34.5.dist-info/DESCRIPTION.rst
Flask_MicroServices-0.34.5.dist-info/METADATA
Flask_MicroServices-0.34.5.dist-info/RECORD
Flask_MicroServices-0.34.5.dist-info/WHEEL
Flask_MicroServices-0.34.5.dist-info/metadata.json
Flask_MicroServices-0.34.5.dist-info/top_level.txt
Flask_MicroServices-0.34.5.dist-info/zip-safe
flask_microservices/__init__.py
flask_microservices/exceptions.py
flask_microservices/__pycache__/__init__.cpython-35.pyc
flask_microservices/__pycache__/exceptions.cpython-35.pyc
flask_microservices/__pycache__/main.cpython-35.pyc
