Metadata-Version: 2.0
Name: Flask-MicroServices
Version: 0.34.5
Summary: Self contained modules and Django style URL routing for Flask.
Home-page: http://github.com/noisek/Flask-MicroServices
Author: Noi Sek
Author-email: noi.t.sek@gmail.com
License: MIT
Requires-Dist: Flask
